NiuLab_download_TikTok_videos/NiuLab_download_TikTok_videos.py
NiuLab_download_TikTok_videos/__init__.py
NiuLab_Download_TikTok_Videos-1.0.0.dist-info/LICENSE
NiuLab_Download_TikTok_Videos-1.0.0.dist-info/METADATA
NiuLab_Download_TikTok_Videos-1.0.0.dist-info/WHEEL
NiuLab_Download_TikTok_Videos-1.0.0.dist-info/top_level.txt
NiuLab_Download_TikTok_Videos-1.0.0.dist-info/RECORD
