Metadata-Version: 2.1
Name: NiuLab-Download-TikTok-Videos
Version: 1.0.0
Summary: Downloads TikTok Videos
Author-email: "Shuo Niu, Abhisan Ghimire" <invictuscreatesanapp@gmail.com>
License: MIT License        
Classifier: Programming Language :: Python :: 3
Classifier: License :: OSI Approved :: MIT License
Classifier: Operating System :: OS Independent
Requires-Python: >=3.7
License-File: LICENSE
